s5commander/__init__.py
s5commander/commander.py
s5commander-0.0.1.dev2.dist-info/LICENSE.md
s5commander-0.0.1.dev2.dist-info/METADATA
s5commander-0.0.1.dev2.dist-info/WHEEL
s5commander-0.0.1.dev2.dist-info/RECORD
