Metadata-Version: 2.1
Name: s5commander
Version: 0.0.1.dev2
Summary: 
License: MIT
Author: Clément POIRET
Author-email: poiret.clement@outlook.fr
Requires-Python: >=3.7,<4.0
Classifier: License :: OSI Approved :: MIT License
Classifier: Programming Language :: Python :: 3
Classifier: Programming Language :: Python :: 3.7
Classifier: Programming Language :: Python :: 3.8
Classifier: Programming Language :: Python :: 3.9
Classifier: Programming Language :: Python :: 3.10
Classifier: Programming Language :: Python :: 3.11
